nepali_calendar_utils/__init__.py
nepali_calendar_utils/calendar_model/date_converters.py
nepali_calendar_utils/calendar_model/nepali_calendar_defaults.py
nepali_calendar_utils/calendar_model/nepali_calendar_model.py
nepali_calendar_utils/calendar_model/nepali_date_converter.py
nepali_calendar_utils/data/custom_calendar.py
nepali_calendar_utils/data/nepali_date_locale.py
nepali_calendar_utils/data/nepali_year_month_map.py
nepali_calendar_utils-2.0.1.dist-info/METADATA
nepali_calendar_utils-2.0.1.dist-info/WHEEL
nepali_calendar_utils-2.0.1.dist-info/licenses/LICENSE
nepali_calendar_utils-2.0.1.dist-info/RECORD
