Metadata-Version: 2.4
Name: nepali_calendar_utils
Version: 2.0.1
Summary: Utilities for working with Nepali dates
Project-URL: Homepage, https://github.com/shivathapaa/nepali_calendar_utils
Project-URL: Documentation, https://github.com/shivathapaa/nepali_calendar_utils/blob/main/README.md
Project-URL: Repository, https://github.com/shivathapaa/nepali_calendar_utils
Project-URL: Bug Tracker, https://github.com/shivathapaa/nepali_calendar_utils/issues
Author-email: Shiva Thapa <query.shivathapaa.dev@gmail.com>
Maintainer-email: Shiva Thapa <query.shivathapaa.dev@gmail.com>
License-Expression: MPL-2.0
License-File: LICENSE
Keywords: date utilities,nepali calendar,nepali date,nepali date utilities
Classifier: Development Status :: 5 - Production/Stable
Classifier: Intended Audience :: Developers
Classifier: License :: OSI Approved :: Mozilla Public License 2.0 (MPL 2.0)
Classifier: Programming Language :: Python
Classifier: Programming Language :: Python :: 3
Classifier: Programming Language :: Python :: 3 :: Only
Classifier: Topic :: Utilities
Requires-Python: >=3.7
